solprimer/clearsky_poa.py
solprimer/clearsky_profile.py
solprimer/convert_epw_csv.py
solprimer/convert_pvgis_csv.py
solprimer/convert_tya_csv.py
solprimer/csvdata_CEC_inverter_data.py
solprimer/csvdata_CEC_module_data.py
solprimer/csvdata_CEC_module_sort.py
solprimer/csvdata_Sandia_module_data.py
solprimer/csvdata_component_list.py
solprimer/csvdata_pandas_read.py
solprimer/datetime_example.py
solprimer/plot_poa_barchart.py
solprimer/plot_poa_graph.py
solprimer/plot_poa_heatmap.py
solprimer/plot_tmy_barchart.py
solprimer/plot_tmy_data.py
solprimer/plot_tmy_heatmap.py
solprimer/plot_tmy_mult.py
solprimer/plot_tmy_noontime.py
solprimer/plot_tmy_vs_clearsky.py
solprimer/power_load_profile.py
solprimer/power_pvgen_direct.py
solprimer/power_pvgen_load.py
solprimer/psychro_display.py
solprimer/solpath_Cartesian_azim_elev.py
solprimer/solpath_Cartesian_mult.py
solprimer/solpath_Cartesian_time_elev.py
solprimer/solpath_polar.py
solprimer/solpath_polar_mult.py
solprimer/spectrum_AM0AM15.py
solprimer/spectrum_blackbody.py
solprimer/sunrise_sunset_time.py
solprimer/test_poa_result.py
solprimer/test_solpos_pvlib.py
solprimer/tmy_location_data.py
solprimer/data-TMY/DATATMY_README.txt
solprimer/data-input/DATAINPUT_README.txt
solprimer/data-output/DATAOUTPUT_README.txt
solprimer/docs/LICENSE.txt
solprimer/docs/README.txt
solprimer/docs/solprimer_20170712.pdf
solprimer/solprim/__init__.py
solprimer/solprim/readcsvfile.py
solprimer/solprim/solarradiation.py
solprimer/solprim/solartimeposition.py
solprimer/solprim/tmyconvert.py
solprimer/solprim/tmyutility.py
solprimer-1.0.1.dist-info/DESCRIPTION.rst
solprimer-1.0.1.dist-info/METADATA
solprimer-1.0.1.dist-info/RECORD
solprimer-1.0.1.dist-info/WHEEL
solprimer-1.0.1.dist-info/metadata.json
solprimer-1.0.1.dist-info/top_level.txt
