Metadata-Version: 2.0
Name: solprimer
Version: 1.0.1
Summary: Solar energy calculation primer
Home-page: UNKNOWN
Author: Gianguido Piani
Author-email: solarprimer@mailbox.org
License: GPLv3+
Keywords: renewable energy solar photovoltaic TMY
Platform: UNKNOWN
Classifier: Development Status :: 4 - Beta
Classifier: Intended Audience :: Education
Classifier: Intended Audience :: Other Audience
Classifier: Topic :: Education
Classifier: Topic :: Scientific/Engineering
Classifier: License :: OSI Approved :: GNU General Public License v3 or later (GPLv3+)
Classifier: Natural Language :: English
Classifier: Programming Language :: Python
Classifier: Programming Language :: Python :: 2
Classifier: Programming Language :: Python :: 3
